anubi/mdns/__init__.py
anubi/mdns/_dnsrecord.py
anubi/mdns/_utility.py
anubi/mdns/dnsenums.py
anubi/mdns/dnspacket.py
anubi/mdns/dnsqrecord.py
anubi/mdns/dnsrrecords.py
anubi/mdns/mdns.py
anubi.mdns-0.1.0a0.dist-info/LICENSE.md
anubi.mdns-0.1.0a0.dist-info/METADATA
anubi.mdns-0.1.0a0.dist-info/WHEEL
anubi.mdns-0.1.0a0.dist-info/top_level.txt
anubi.mdns-0.1.0a0.dist-info/RECORD
