Metadata-Version: 2.1
Name: anubi.mdns
Version: 0.1.0a0
Summary: A simple pure python implementation of a multicast DNS responder
Home-page: https://github.com/Anubi85/mDNS
Author: Andrea Parisotto
License: MIT
Keywords: Multicast DNS,mDNS
Platform: UNKNOWN
Classifier: Development Status :: 3 - Alpha
Classifier: Intended Audience :: Developers
Classifier: Intended Audience :: System Administrators
Classifier: License :: OSI Approved :: MIT License
Classifier: Operating System :: OS Independent
Classifier: Topic :: Software Development :: Libraries
Classifier: Programming Language :: Python :: 3
Classifier: Programming Language :: Python :: 3.7
Classifier: Programming Language :: Python :: 3.8
Requires-Python: >=3
